<?xml version="1.0"?>
<!DOCTYPE hibernate-mapping PUBLIC "-//Hibernate/Hibernate Mapping DTD 3.0//EN"
"http://www.hibernate.org/dtd/hibernate-mapping-3.0.dtd">
<!-- Generated 16-08-2021 14:22:23 by Hibernate Tools 4.3.1 -->
<hibernate-mapping>
    <class name="com.grupobios.bioslis.bs.CfgBacmetodosresistencia" table="CFG_BACMETODOSRESISTENCIA" schema="BIOSLIS" optimistic-lock="version">
        <id name="cmrIdmetodoresistencia" type="boolean">
            <column name="CMR_IDMETODORESISTENCIA" precision="1" scale="0" />
        	<generator class="sequence">
        		<param name="sequence">BIOSLIS.SEQ_CFG_BACMETODOSRESISTENCIA</param>
        	</generator>
        </id>
        <property name="cmrCodigo" type="string">
            <column name="CMR_CODIGO" length="40" not-null="true" />
        </property>
        <property name="cmrDescripcion" type="string">
            <column name="CMR_DESCRIPCION" length="160" />
        </property>
        <property name="cmrActivo" type="string">
            <column name="CMR_ACTIVO" length="1" />
        </property>
        <property name="cmrHost" type="string">
            <column name="CMR_HOST" length="80" />
        </property>
    </class>
</hibernate-mapping>
