<?xml version="1.0"?>
<!DOCTYPE hibernate-mapping PUBLIC "-//Hibernate/Hibernate Mapping DTD 3.0//EN"
"http://www.hibernate.org/dtd/hibernate-mapping-3.0.dtd">
<!-- Generated 16-08-2021 14:22:23 by Hibernate Tools 4.3.1 -->
<hibernate-mapping>
    <class name="com.grupobios.bioslis.bs.CfgBacmedioscultivos" table="CFG_BACMEDIOSCULTIVOS" schema="BIOSLIS" optimistic-lock="version">
        <id name="cbmcIdmediocultivo" type="byte">
            <column name="CBMC_IDMEDIOCULTIVO" precision="2" scale="0" />
        	<generator class="sequence">
        		<param name="sequence">BIOSLIS.SEQ_CFG_BACMEDIOSCULTIVOS</param>
        	</generator>
        </id>
        <property name="cbmcCodigo" type="string">
            <column name="CBMC_CODIGO" length="40" />
        </property>
        <property name="cbmcDescripcion" type="string">
            <column name="CBMC_DESCRIPCION" length="160" />
        </property>
        <property name="cbmcPrefijo" type="string">
            <column name="CBMC_PREFIJO" length="8" />
        </property>
        <property name="cbmcActivo" type="string">
            <column name="CBMC_ACTIVO" length="1" />
        </property>
        <property name="cbmcSort" type="java.lang.Byte">
            <column name="CBMC_SORT" precision="2" scale="0" />
        </property>
    </class>
</hibernate-mapping>
